{
    "output_device": "Speakers",
    "mic_device": "Mic 1",
    "mic_sensitivity": 50,
    "speaker_voice": "Male",
    "speaker_volume": 70,
    "privacy_model": "Standard",
    "dnd_mode": false,
    "enable_notifications": true,
    "keywords": [
        "violence",
        "confident",
        "loneliness",
        "pressure",
        "happy",
        "loss",
        "abuse",
        "pills",
        "joy",
        "guilt",
        "alone",
        "betrayal",
        "quite",
        "rejection",
        "jobless",
        "pain",
        "scared",
        "breakup",
        "lost",
        "drained",
        "uncertain",
        "nightmare",
        "shame",
        "self-harm",
        "hopelessness",
        "regretful",
        "overdose",
        "stress",
        "cheating",
        "quit",
        "deadline",
        "fear",
        "weak",
        "resssign",
        "empty",
        "excited",
        "worry",
        "inspired",
        "hate myself",
        "depression",
        "unemployment",
        "control",
        "threat",
        "tough",
        "useless",
        "worthless",
        "unwanted",
        "failure",
        "trauma",
        "anger",
        "overwork",
        "peaceful",
        "sex",
        "not enough",
        "suffocating",
        "bullying",
        "suicide",
        "sadness",
        "calm",
        "overwhelmed",
        "painkillers",
        "blood",
        "hemesh",
        "depressed",
        "crying",
        "change",
        "resign",
        "insecure",
        "workload",
        "hopeless",
        "shattered",
        "work",
        "unsafe",
        "tired",
        "danger",
        "divorce",
        "her",
        "grateful",
        "helpless",
        "strong",
        "knife",
        "unloved",
        "self-doubt",
        "motivated",
        "broken",
        "anxiety",
        "nervous",
        "regret",
        "unworthy",
        "stop",
        "panic",
        "stressed",
        "ignored",
        "frustration",
        "burnout",
        "jealousy",
        "pressured",
        "deadline_is_over",
        "end life",
        "unstable",
        "abandonment",
        "mistake",
        "devastated",
        "cutting",
        "recovery"
    ],
    "trigger_word_threshold": 3,
    "telegram_password": "1234"
}